astro/__init__.py
astro/deconvolution/__init__.py
astro/deconvolution/deconvolve.py
astro/deconvolution/linear.py
astro/deconvolution/wavelet_filters.py
astro/denoising/__init__.py
astro/denoising/denoise.py
astro/denoising/noise.py
astro/denoising/wavelet.py
astro/tests/__init__.py
astro/tests/test_denoising.py
pysap_astro-0.0.3.dist-info/LICENSE
pysap_astro-0.0.3.dist-info/METADATA
pysap_astro-0.0.3.dist-info/WHEEL
pysap_astro-0.0.3.dist-info/top_level.txt
pysap_astro-0.0.3.dist-info/RECORD
