Metadata-Version: 2.1
Name: pysap-astro
Version: 0.0.3
Summary: Python Sparse data Analysis Package external ASTRO plugin.
Home-page: https://github.com/CEA-COSMIC/pysap-astro
Author: 
Requires-Dist: sf-tools >=2.0.4
